bizon/__main__.py
bizon/utils.py
bizon/alerting/__init__.py
bizon/alerting/alerts.py
bizon/alerting/models.py
bizon/alerting/slack/__init__.py
bizon/alerting/slack/config.py
bizon/alerting/slack/handler.py
bizon/cli/__init__.py
bizon/cli/main.py
bizon/cli/utils.py
bizon/common/models.py
bizon/common/errors/backoff.py
bizon/common/errors/errors.py
bizon/connectors/destinations/bigquery/config/bigquery.example.yml
bizon/connectors/destinations/bigquery/config/bigquery_incremental.example.yml
bizon/connectors/destinations/bigquery/src/config.py
bizon/connectors/destinations/bigquery/src/destination.py
bizon/connectors/destinations/bigquery_streaming/config/bigquery_streaming.example.yml
bizon/connectors/destinations/bigquery_streaming/src/config.py
bizon/connectors/destinations/bigquery_streaming/src/destination.py
bizon/connectors/destinations/bigquery_streaming_v2/config/bigquery_streaming_v2.example.yml
bizon/connectors/destinations/bigquery_streaming_v2/src/config.py
bizon/connectors/destinations/bigquery_streaming_v2/src/destination.py
bizon/connectors/destinations/bigquery_streaming_v2/src/proto_utils.py
bizon/connectors/destinations/file/config/file.example.yml
bizon/connectors/destinations/file/config/file_incremental.example.yml
bizon/connectors/destinations/file/src/config.py
bizon/connectors/destinations/file/src/destination.py
bizon/connectors/destinations/logger/config/logger.example.yml
bizon/connectors/destinations/logger/config/logger_incremental.example.yml
bizon/connectors/destinations/logger/src/config.py
bizon/connectors/destinations/logger/src/destination.py
bizon/connectors/sources/cycle/config/cycle.example.yml
bizon/connectors/sources/cycle/src/source.py
bizon/connectors/sources/cycle/tests/cycle_customers.py
bizon/connectors/sources/dummy/config/dummy.example.yml
bizon/connectors/sources/dummy/src/fake_api.py
bizon/connectors/sources/dummy/src/source.py
bizon/connectors/sources/dummy/tests/dummy_pipeline.py
bizon-0.3.0.dist-info/METADATA
bizon-0.3.0.dist-info/WHEEL
bizon-0.3.0.dist-info/entry_points.txt
bizon-0.3.0.dist-info/licenses/LICENSE
bizon-0.3.0.dist-info/RECORD
