Metadata-Version: 2.4
Name: bizon
Version: 0.3.0
Summary: Extract and load your data reliably from API Clients with native fault-tolerant and checkpointing mechanism.
Author-email: Antoine Balliet <antoine.balliet@gmail.com>, Anas El Mhamdi <anas.elmhamdi@gmail.com>
License-File: LICENSE
Requires-Python: <3.13,>=3.9
Requires-Dist: backoff>=2.2.1
Requires-Dist: click>=8.1.7
Requires-Dist: dpath>=2.2.0
Requires-Dist: google-cloud-storage>=2.17.0
Requires-Dist: loguru>=0.7.2
Requires-Dist: orjson>=3.10.16
Requires-Dist: pendulum>=3.0.0
Requires-Dist: polars>=1.16.0
Requires-Dist: pyarrow>=16.1.0
Requires-Dist: pydantic-extra-types>=2.9.0
Requires-Dist: pydantic>=2.8.2
Requires-Dist: python-dotenv>=1.0.1
Requires-Dist: pytz>=2024.2
Requires-Dist: pyyaml>=6.0.1
Requires-Dist: requests>=2.28.2
Requires-Dist: simplejson>=3.20.1
Requires-Dist: sqlalchemy>=2.0.32
Requires-Dist: tenacity>=9.0.0
Provides-Extra: bigquery
Requires-Dist: google-cloud-bigquery-storage>=2.25.0; extra == 'bigquery'
Requires-Dist: google-cloud-bigquery>=3.25.0; extra == 'bigquery'
Requires-Dist: protobuf>=4.24.0; extra == 'bigquery'
Requires-Dist: sqlalchemy-bigquery>=1.11.0; extra == 'bigquery'
Provides-Extra: datadog
Requires-Dist: datadog>=0.50.2; extra == 'datadog'
Requires-Dist: ddtrace>=3.10.0; extra == 'datadog'
Provides-Extra: gsheets
Requires-Dist: gspread>=6.1.2; extra == 'gsheets'
Provides-Extra: kafka
Requires-Dist: avro>=1.12.0; extra == 'kafka'
Requires-Dist: confluent-kafka>=2.6.0; extra == 'kafka'
Requires-Dist: fastavro>=1.9.7; extra == 'kafka'
Requires-Dist: kafka-python>=2.0.2; extra == 'kafka'
Provides-Extra: postgres
Requires-Dist: psycopg2-binary>=2.9.9; extra == 'postgres'
Provides-Extra: rabbitmq
Requires-Dist: pika>=1.3.2; extra == 'rabbitmq'
